songs_to_youtube/commands/concat/concat.command
songs_to_youtube/commands/render/blurred background.command
songs_to_youtube/commands/render/no background.command
songs_to_youtube/commands/render/solid color background.command
songs_to_youtube/commands/render/vertical blurred background.command
songs_to_youtube/config/default.ini
songs_to_youtube/const.py
songs_to_youtube/field.py
songs_to_youtube/image/default.jpg
songs_to_youtube/image/icon.ico
songs_to_youtube/image/multiple-values.png
songs_to_youtube/log.py
songs_to_youtube/main.py
songs_to_youtube/metadata.py
songs_to_youtube/metadata_table_widget.py
songs_to_youtube/progress_window.py
songs_to_youtube/render.py
songs_to_youtube/settings.py
songs_to_youtube/song_settings_widget.py
songs_to_youtube/song_tree_widget.py
songs_to_youtube/song_tree_widget_item.py
songs_to_youtube/template.py
songs_to_youtube/ui/adduser.ui
songs_to_youtube/ui/mainwindow.ui
songs_to_youtube/ui/metadata.ui
songs_to_youtube/ui/settingswindow.ui
songs_to_youtube/ui/songsettingswindow.ui
songs_to_youtube/upload.py
songs_to_youtube/utils.py
songs_to_youtube-0.13.1.dist-info/METADATA
songs_to_youtube-0.13.1.dist-info/WHEEL
songs_to_youtube-0.13.1.dist-info/entry_points.txt
songs_to_youtube-0.13.1.dist-info/RECORD
