Metadata-Version: 2.1
Name: songs-to-youtube
Version: 0.13.1
Summary: Application to upload songs to YouTube
Author: 7x11x13
Author-email: x7x11x13@gmail.com
Requires-Python: >=3.10,<3.12
Classifier: Programming Language :: Python :: 3
Classifier: Programming Language :: Python :: 3.10
Classifier: Programming Language :: Python :: 3.11
Requires-Dist: mutagen (>=1.47.0,<2.0.0)
Requires-Dist: pathvalidate (>=3.2.0,<4.0.0)
Requires-Dist: psutil (>=5.9.6,<6.0.0)
Requires-Dist: pyside6 (==6.6.1)
Requires-Dist: youtube-up (>=0.5.0,<0.6.0)
